{"id": "javascript_0", "result": [{"validateUserInput": "{\"inputField\": \"userInputField\", \"isComplete\": \"true\"}"}], "input_token_count": 180, "output_token_count": 31, "latency": 1.1311779022216797}
{"id": "javascript_1", "result": [{"getActiveDataEntries": "{\"attribute\": \"data-active\", \"listElement\": \"listElement\", \"value\": true}"}], "input_token_count": 266, "output_token_count": 36, "latency": 1.251866102218628}
{"id": "javascript_2", "result": [{"extractLastTransactionId": "{\"filepath\": \"/var/log/db.log\", \"status\": \"['completed', 'failed']\", \"encoding\": \"utf-8\", \"processFunction\": \"processFunction\"}"}], "input_token_count": 326, "output_token_count": 57, "latency": 1.9116051197052002}
{"id": "javascript_3", "result": [{"submitAtCoordinate": "{\"action\": \"submit\", \"formId\": \"loginForm\", \"coordinates\": \"[0.3, 0.6]\"}"}], "input_token_count": 264, "output_token_count": 45, "latency": 1.5330243110656738}
{"id": "javascript_4", "result": [{"emailFormatValidator": "{\"domain\": \"domain.com\", \"email\": \"example@domain.com\"}"}], "input_token_count": 200, "output_token_count": 33, "latency": 2.250643014907837}
{"id": "javascript_5", "result": "```python\nmanageReactState(\n    store={\n        \"initialState\": initialStateObject,\n        \"reducers\": reducersMap,\n        \"middlewares\": [loggerMiddleware],\n        \"enhancers\": [applyMiddleware('myMiddleWare')]\n    },\n    context=\"ReactContext\",\n    hooks={\n        \"useStateSelector\": useStateSelectorHook,\n        \"useDispatchAction\": useDispatchActionHook\n    }\n)\n```", "input_token_count": 482, "output_token_count": 105, "latency": 4.507354736328125}
{"id": "javascript_6", "result": [{"mapTransitions": "{\"category\": \"transition\", \"limit\": \"4\"}"}], "input_token_count": 208, "output_token_count": 27, "latency": 1.1876070499420166}
{"id": "javascript_7", "result": [{"getNextKeyValues": "{\"ctx\": \"dataAnalysisContext\", \"currentKey\": \"userId\"}"}], "input_token_count": 246, "output_token_count": 31, "latency": 1.1953411102294922}
{"id": "javascript_8", "result": [{"doesEmailInputExist": "{\"formElem\": \"emailForm\", \"inputName\": \"emailAddress\"}"}], "input_token_count": 187, "output_token_count": 33, "latency": 1.1771512031555176}
{"id": "javascript_9", "result": "Sure, I can help you with that. Here is a JavaScript function that you can use to analyze the JSON payload and trigger the corresponding processing logic if the key is present:\n\n```javascript\nfunction validateApiResponse(jsonPayload, keyToCheck, processingCallback) {\n    try {\n        const parsedPayload = JSON.parse(jsonPayload);\n        if (parsedPayload.hasOwnProperty(keyToCheck)) {\n            processingCallback(parsedPayload[keyToCheck]);\n        } else {\n            console.log(`Key \"${keyToCheck}\" not found in the JSON payload.`);\n        }\n    } catch (error) {\n        console.error('Error parsing JSON payload:', error);\n    }\n}\n\n// Example usage:\nconst responseData = '{\"expectedKey\": \"someValue\", \"otherKey\": \"otherValue\"}';\nconst expectedKey = 'expectedKey';\nconst processKeyFunction = (value) => {\n    console.log(`Processing value for key \"${expectedKey}\":`, value);\n};\n\nvalidateApiResponse(responseData, expectedKey, processKeyFunction);\n```\n\nIn this example:\n- `responseData` is the JSON payload you want to validate.\n- `expectedKey` is the key you are checking for in the JSON payload.\n- `processKeyFunction` is the callback function that will be executed if the key is present in the JSON payload.\n\nYou can replace `responseData`, `expectedKey`, and `processKeyFunction` with your actual data and processing logic.", "input_token_count": 268, "output_token_count": 336, "latency": 8.957884788513184}
{"id": "javascript_10", "result": [{"fetchSalesDepartmentRecords": "{\"databaseName\": \"employeeRecords\", \"queryFunction\": \"getSales\"}"}], "input_token_count": 251, "output_token_count": 36, "latency": 7.971881151199341}
{"id": "javascript_11", "result": [{"prioritizeAndSort": "{\"items\": \"myItemList\", \"priorityStatus\": \"urgent\", \"ascending\": \"true\"}"}], "input_token_count": 281, "output_token_count": 40, "latency": 1.4664411544799805}
{"id": "javascript_12", "result": "```python\nimport requests\n\ndef performDataFetch(apiEndpoint, requestConfig, expectedResponse, handleErrors=False):\n    try:\n        response = requests.request(\n            method=requestConfig['method'],\n            url=apiEndpoint,\n            headers=requestConfig.get('headers', {}),\n            data=requestConfig.get('body', {})\n        )\n        response.raise_for_status()\n        data = response.json()\n\n        if data == expectedResponse:\n            return data\n        else:\n            return f\"Error: Expected response {expectedResponse} but got {data}\"\n    except requests.exceptions.RequestException as e:\n        if handleErrors:\n            return f\"An error occurred: {e}\"\n        else:\n            raise\n\napiEndpoint = 'https://api.example.com/data'\nrequestConfig = {\"method\": \"GET\"}\nexpectedResponse = {\"key\": \"value\"}\n\nresult = performDataFetch(apiEndpoint, requestConfig, expectedResponse)\nprint(result)\n```", "input_token_count": 410, "output_token_count": 235, "latency": 6.49219822883606}
{"id": "javascript_13", "result": [{"DynamicChartGenerator": "{\"dashboard\": \"dashboardElement\", \"options\": \"{}\", \"scalingFactor\": \"3\", \"userData\": \"userDataArray\"}"}], "input_token_count": 305, "output_token_count": 45, "latency": 1.4577569961547852}
{"id": "javascript_14", "result": [{"chartDataAccessorFactory": "{\"chart\": \"{\\\"nm\\\": \\\"BarChart\\\", \\\"mn\\\": \\\"chartModule\\\"}\", \"configObject\": \"\\\"config\\\"\", \"library\": \"\\\"visualizationLibrary\\\"\"}"}], "input_token_count": 360, "output_token_count": 56, "latency": 1.9109430313110352}
{"id": "javascript_15", "result": [{"ChartSeriesGenerator": "{\"chartLayout\": \"chartLayoutObject\", \"color\": \"defaultColor\", \"data\": \"dataPointsArray\", \"labels\": \"axisLabelsArray\"}"}], "input_token_count": 308, "output_token_count": 47, "latency": 2.764359951019287}
{"id": "javascript_16", "result": [{"rotateVertices": "{\"angle\": \"30\", \"pivot\": \"[12, 17]\", \"vertices\": \"[[10, 15], [20, 25]]\"}"}], "input_token_count": 292, "output_token_count": 56, "latency": 1.8873019218444824}
{"id": "javascript_17", "result": [{"generateNotificationHandler": "{\"app\": \"app\", \"priorityLevel\": \"3\", \"messagingService\": \"messagingSvc\", \"notificationType\": \"2\"}"}], "input_token_count": 313, "output_token_count": 48, "latency": 1.462364912033081}
{"id": "javascript_18", "result": [{"calculateFinalVelocity": "{\"gravity\": \"9.8\", \"initialVelocity\": \"0\", \"time\": \"5\"}"}], "input_token_count": 246, "output_token_count": 40, "latency": 2.2970287799835205}
{"id": "javascript_19", "result": [{"configureShaderMaterial": "{\"property\": \"materialProps\", \"textures\": \"textureList\", \"object3D\": \"meshObject\"}"}], "input_token_count": 277, "output_token_count": 39, "latency": 1.335184097290039}
{"id": "javascript_20", "result": [{"buttonAddClickHandler": "{\"element\": \"myButton\", \"callback\": \"handleButtonClick\", \"options\": \"{\\\"stopPropagation\\\": true}\"}"}], "input_token_count": 256, "output_token_count": 43, "latency": 1.3371798992156982}
{"id": "javascript_21", "result": [{"findProductById": "{\"products\": \"['Product A', 'Product B', 'Product C']\", \"id\": \"123\"}"}], "input_token_count": 196, "output_token_count": 40, "latency": 1.298309087753296}
{"id": "javascript_22", "result": [{"resetStateProperty": "{\"stateProperty\": \"userSession\"}"}], "input_token_count": 134, "output_token_count": 23, "latency": 1.3112390041351318}
{"id": "javascript_23", "result": [{"createAuthToken": "{\"options\": \"{\\\"issuer\\\": \\\"myapp.net\\\", \\\"role\\\": \\\"admin\\\", \\\"algorithm\\\": \\\"HS256\\\"}\", \"username\": \"johndoe\", \"validity\": \"3600\"}"}], "input_token_count": 327, "output_token_count": 65, "latency": 2.0138790607452393}
{"id": "javascript_24", "result": [{"getUniqueSorted": "{\"array\": \"[3, 1, 2, 1, 4, 3]\"}"}], "input_token_count": 180, "output_token_count": 38, "latency": 1.308824062347412}
{"id": "javascript_25", "result": [{"trackSubmitWithValidation": "{\"obj\": \"formHandler\", \"validationFlags\": \"['isRequired', 'isValidEmail']\"}"}], "input_token_count": 235, "output_token_count": 38, "latency": 1.2558200359344482}
{"id": "javascript_26", "result": [{"contentUpdater": "{\"action\": \"update\", \"elementID\": \"contentBox\", \"newContent\": \"Hello World\"}"}], "input_token_count": 236, "output_token_count": 37, "latency": 1.2616009712219238}
{"id": "javascript_27", "result": [{"validateReactProp": "{\"componentName\": \"UserProfile\", \"obj\": \"serviceProvider\"}"}], "input_token_count": 253, "output_token_count": 30, "latency": 1.7017569541931152}
{"id": "javascript_28", "result": [{"filterBooksByAuthor": "{\"author\": \"J.K. Rowling\", \"library\": \"['bookA','bookB','bookC']\"}"}], "input_token_count": 211, "output_token_count": 43, "latency": 1.468066930770874}
{"id": "javascript_29", "result": [{"EventScheduler": "{\"events\": \"{\\\"setupStage\\\": {\\\"event\\\": \\\"setupStageFunction\\\", \\\"prerequisites\\\": []}, \\\"cleanupStage\\\": {\\\"event\\\": \\\"cleanStageFunction\\\", \\\"prerequisites\\\": [\\\"setupStage\\\"]}}\", \"concurrencyLimit\": \"3\"}"}], "input_token_count": 271, "output_token_count": 76, "latency": 4.077007055282593}
{"id": "javascript_30", "result": [{"setText": "{\"newText\": \"Hello, World!\", \"start\": \"5\", \"length\": \"7\"}"}], "input_token_count": 221, "output_token_count": 35, "latency": 1.2080440521240234}
{"id": "javascript_31", "result": [{"transformAllDecoratorsOfDeclaration": "{\"container\": \"myContainer\", \"node\": \"myNode\"}"}], "input_token_count": 194, "output_token_count": 33, "latency": 1.242271900177002}
{"id": "javascript_32", "result": [{"pollQueue": "{\"queue\": \"fileWatchQueue\", \"pollingInterval\": \"500\", \"pollIndex\": \"0\", \"chunkSize\": \"10\"}"}], "input_token_count": 301, "output_token_count": 47, "latency": 1.534593105316162}
{"id": "javascript_33", "result": [{"emitNewLineBeforeLeadingComments": "{\"leadingComments\": \"[]\", \"lineMap\": \"tsLineMap\", \"node\": \"42\", \"writer\": \"tsWriter\"}"}], "input_token_count": 293, "output_token_count": 51, "latency": 2.145185947418213}
{"id": "javascript_34", "result": [{"forEachType": "{\"f\": \"processType\", \"type\": \"unionTypeObj\"}"}], "input_token_count": 218, "output_token_count": 29, "latency": 1.0564608573913574}
{"id": "javascript_35", "result": "Sure, I can help with that. Please provide the TypeScript declaration objects for the parameter and the variable declaration.", "input_token_count": 227, "output_token_count": 23, "latency": 1.2461271286010742}
{"id": "javascript_36", "result": "Sure, I can help with that. Could you please provide the break node that you want to update?", "input_token_count": 203, "output_token_count": 21, "latency": 1.1225590705871582}
{"id": "javascript_37", "result": [{"addInitializedPropertyStatements": "{\"property\": \"['width', 'height']\", \"receiver\": \"'shape'\", \"statements\": \"'shapeStatements'\"}"}], "input_token_count": 276, "output_token_count": 44, "latency": 5.6481170654296875}
{"id": "javascript_38", "result": [{"getDirectoryToWatchFromFailedLookupLocationDirectory": "{\"dir\": \"node_modules/react\", \"dirPath\": \"/projects/myApp/node_modules/react\"}"}], "input_token_count": 223, "output_token_count": 47, "latency": 2.4314472675323486}
{"id": "javascript_39", "result": "Sure, I can help with that. Please provide the function declaration object 'funcDeclaration' and its parameters array 'funcParameters'.", "input_token_count": 243, "output_token_count": 26, "latency": 0.9905667304992676}
{"id": "javascript_40", "result": [{"assignOwnDefaults": "{\"key\": \"maxItems\", \"object\": \"{}\", \"objectValue\": \"12\", \"sourceValue\": \"10\"}"}], "input_token_count": 308, "output_token_count": 45, "latency": 1.480696201324463}
{"id": "javascript_41", "result": [{"queue_1": "{\"concurrency\": \"5\", \"worker\": \"myWorkerFunction\"}"}], "input_token_count": 258, "output_token_count": 30, "latency": 2.609375}
{"id": "javascript_42", "result": [{"B": "{\"e\": \"null\", \"n\": \"0.0\", \"t\": \"5.0\"}"}], "input_token_count": 283, "output_token_count": 35, "latency": 2.588960647583008}
{"id": "javascript_43", "result": [{"invokeCallback": "{\"callback\": \"processResult\", \"error\": \"null\", \"value\": \"Operation successful\"}"}], "input_token_count": 240, "output_token_count": 34, "latency": 1.1816470623016357}
{"id": "javascript_44", "result": [{"skipThrough": "{\"c\": \"processNode\", \"node\": \"currentNode\", \"st\": \"nodeState\"}"}], "input_token_count": 248, "output_token_count": 36, "latency": 1.2712070941925049}
{"id": "javascript_45", "result": [{"Sde": "{\"e\": \"{\\\"startingCwd\\\": \\\"/home/user/projects\\\"}\", \"t\": \"https://github.com/yarnpkg/berry\"}"}], "input_token_count": 276, "output_token_count": 50, "latency": 1.6609370708465576}
{"id": "javascript_46", "result": [{"vOe": "{\"r\": \"packageInfo\", \"e\": \"version\", \"t\": \"1.2.3\"}"}], "input_token_count": 253, "output_token_count": 38, "latency": 1.3043150901794434}
{"id": "javascript_47", "result": [{"sTe": "{\"e\": \"2023-04-15\", \"r\": \"2023-04-01\", \"t\": \"days\"}"}], "input_token_count": 228, "output_token_count": 50, "latency": 1.5403928756713867}
{"id": "javascript_48", "result": [{"updateDOMListeners": "{\"oldVnode\": \"oldVirtualNode\", \"vnode\": \"newVirtualNode\"}"}], "input_token_count": 219, "output_token_count": 34, "latency": 1.1393580436706543}
{"id": "javascript_49", "result": [{"convertEnumeratedValue": "{\"key\": \"contenteditable\", \"value\": \"plaintext-only\"}"}], "input_token_count": 212, "output_token_count": 33, "latency": 1.1488730907440186}
