{"id": "javascript_0", "result": "[validateUserInput(inputField='userInputField', isComplete='true')]", "input_token_count": 398, "output_token_count": 17, "latency": 1.0931191444396973}
{"id": "javascript_1", "result": "[getActiveDataEntries(listElement=listElement, attribute='data-active', value=True)]", "input_token_count": 479, "output_token_count": 18, "latency": 0.8637347221374512}
{"id": "javascript_2", "result": "[extractLastTransactionId(filepath='/var/log/db.log', status=['completed', 'failed'], encoding='utf-8', processFunction='processFunction')]", "input_token_count": 542, "output_token_count": 33, "latency": 1.1788158416748047}
{"id": "javascript_3", "result": "[submitAtCoordinate(action='submit', formId='loginForm', coordinates=[0.3, 0.6])]", "input_token_count": 477, "output_token_count": 26, "latency": 1.2687139511108398}
{"id": "javascript_4", "result": "[emailFormatValidator(email='example@domain.com', domain='domain.com')]", "input_token_count": 411, "output_token_count": 17, "latency": 0.7043609619140625}
{"id": "javascript_5", "result": "[manageReactState(store={'initialState': initialStateObject, 'reducers': reducersMap, 'middlewares': [loggerMiddleware], 'enhancers': [applyMiddleware('myMiddleware')]}, context='React.createContext()', hooks={'useStateSelectorHook': useStateSelectorHook, 'useDispatchActionHook': useDispatchActionHook})]", "input_token_count": 672, "output_token_count": 73, "latency": 1.4428839683532715}
{"id": "javascript_6", "result": "[mapTransitions(category='transition', limit=4)]", "input_token_count": 424, "output_token_count": 12, "latency": 1.6232709884643555}
{"id": "javascript_7", "result": "[getNextKeyValues(ctx=dataAnalysisContext, currentKey='userId')]", "input_token_count": 458, "output_token_count": 17, "latency": 0.49717187881469727}
{"id": "javascript_8", "result": "[doesEmailInputExist(formElem='emailForm', inputName='emailAddress')]", "input_token_count": 404, "output_token_count": 18, "latency": 1.073378086090088}
{"id": "javascript_9", "result": "[validateApiResponse(jsonPayload=responseData, keyToCheck=expectedKey, processingCallback=processKeyFunction)]", "input_token_count": 485, "output_token_count": 24, "latency": 1.1820061206817627}
{"id": "javascript_10", "result": "[fetchSalesDepartmentRecords(databaseName='employeeRecords', queryFunction=getSales)]", "input_token_count": 452, "output_token_count": 17, "latency": 1.1488161087036133}
{"id": "javascript_11", "result": "[prioritizeAndSort(items=myItemList, priorityStatus='urgent', ascending='true')]", "input_token_count": 494, "output_token_count": 23, "latency": 1.0811741352081299}
{"id": "javascript_12", "result": "[performDataFetch(apiEndpoint='https://api.example.com/data', requestConfig='{\"method\": \"GET\"}', expectedResponse='{\"key\": \"value\"}', handleErrors='true')]", "input_token_count": 618, "output_token_count": 40, "latency": 0.9547998905181885}
{"id": "javascript_13", "result": "[DynamicChartGenerator(userData=userDataArray, scalingFactor=3, dashboard=dashboardElement)]", "input_token_count": 519, "output_token_count": 20, "latency": 0.8524770736694336}
{"id": "javascript_14", "result": "[chartDataAccessorFactory(chart={\"nm\": \"BarChart\", \"mn\": \"chartModule\"}, library=visualizationLibrary, configObject=\"config\")]", "input_token_count": 568, "output_token_count": 33, "latency": 1.0353848934173584}
{"id": "javascript_15", "result": "[ChartSeriesGenerator(labels=axisLabelsArray, data=dataPointsArray, color=defaultColor, chartLayout=chartLayoutObject)]", "input_token_count": 528, "output_token_count": 27, "latency": 1.5076241493225098}
{"id": "javascript_16", "result": "[rotateVertices(vertices=\"[[10, 15], [20, 25]]\", pivot=\"[12, 17]\", angle=\"30\")]", "input_token_count": 501, "output_token_count": 39, "latency": 1.7840418815612793}
{"id": "javascript_17", "result": "[generateNotificationHandler(app='app', priorityLevel='3', messagingService='messagingSvc', notificationType='2')]", "input_token_count": 525, "output_token_count": 27, "latency": 1.2220549583435059}
{"id": "javascript_18", "result": "[calculateFinalVelocity(time=5, gravity=9.81, initialVelocity=0)]", "input_token_count": 457, "output_token_count": 20, "latency": 1.334214210510254}
{"id": "javascript_19", "result": "[configureShaderMaterial(property=materialProps, textures=textureList, object3D=meshObject)]", "input_token_count": 487, "output_token_count": 21, "latency": 1.0138769149780273}
{"id": "javascript_20", "result": "[buttonAddClickHandler(element=\"myButton\", callback=\"handleButtonClick\", options='{\"stopPropagation\": true}')]", "input_token_count": 472, "output_token_count": 26, "latency": 1.329157829284668}
{"id": "javascript_21", "result": "[findProductById(products='[\"Product A\", \"Product B\", \"Product C\"]', id='123')]", "input_token_count": 415, "output_token_count": 28, "latency": 0.8138890266418457}
{"id": "javascript_22", "result": "[resetStateProperty(stateProperty=\"userSession\")]", "input_token_count": 350, "output_token_count": 11, "latency": 1.7111780643463135}
{"id": "javascript_23", "result": "[createAuthToken(username='johndoe', validity='3600', options='{\"issuer\": \"myapp.net\", \"role\": \"admin\", \"algorithm\": \"HS256\"}')]", "input_token_count": 535, "output_token_count": 46, "latency": 2.449488878250122}
{"id": "javascript_24", "result": "[getUniqueSorted(array=\"[3, 1, 2, 1, 4, 3]\")]", "input_token_count": 392, "output_token_count": 26, "latency": 0.9167017936706543}
{"id": "javascript_25", "result": "[trackSubmitWithValidation(obj=\"formHandler\", validationFlags=[\"isRequired\", \"isValidEmail\"])],", "input_token_count": 452, "output_token_count": 22, "latency": 1.2097530364990234}
{"id": "javascript_26", "result": "[contentUpdater(elementID='contentBox', newContent='Hello World', action='update')]", "input_token_count": 455, "output_token_count": 21, "latency": 0.9371621608734131}
{"id": "javascript_27", "result": "[validateReactProp(obj='serviceProvider', componentName='UserProfile')]", "input_token_count": 468, "output_token_count": 16, "latency": 1.5208561420440674}
{"id": "javascript_28", "result": "[filterBooksByAuthor(library=\"[bookA, bookB, bookC]\", author=\"J.K. Rowling\")]", "input_token_count": 427, "output_token_count": 27, "latency": 1.2419102191925049}
{"id": "javascript_29", "result": "[EventScheduler(events={\"setupStage\": \"setupStageFunction\", \"cleanupStage\": \"cleanStageFunction\"}, concurrencyLimit=\"3\")]", "input_token_count": 485, "output_token_count": 31, "latency": 1.1296169757843018}
{"id": "javascript_30", "result": "[setText(newText=\"Hello, World!\", start=5, length=7)]", "input_token_count": 441, "output_token_count": 18, "latency": 1.9370357990264893}
{"id": "javascript_31", "result": "[transformAllDecoratorsOfDeclaration(node='myNode', container='myContainer')]", "input_token_count": 409, "output_token_count": 18, "latency": 1.0612680912017822}
{"id": "javascript_32", "result": "[pollQueue(queue='fileWatchQueue', pollingInterval='500', pollIndex='0', chunkSize='10')]", "input_token_count": 518, "output_token_count": 28, "latency": 1.5326330661773682}
{"id": "javascript_33", "result": "[emitNewLineBeforeLeadingComments(lineMap='tsLineMap', writer='tsWriter', node=42, leadingComments=[])", "input_token_count": 511, "output_token_count": 29, "latency": 1.0749952793121338}
{"id": "javascript_34", "result": "[forEachType(type=unionTypeObj, f=processType)]", "input_token_count": 437, "output_token_count": 15, "latency": 0.8231539726257324}
{"id": "javascript_35", "result": "[areDeclarationFlagsIdentical(left=parameterObject, right=variableDeclarationObject)]", "input_token_count": 443, "output_token_count": 17, "latency": 0.6424560546875}
{"id": "javascript_36", "result": "[updateBreak(node=\"breakNode\", label=\"loopEnd\")]", "input_token_count": 421, "output_token_count": 14, "latency": 0.9266979694366455}
{"id": "javascript_37", "result": "[addInitializedPropertyStatements(statements=shapeStatements, property=['width', 'height'], receiver='shape')]", "input_token_count": 489, "output_token_count": 26, "latency": 1.288949966430664}
{"id": "javascript_38", "result": "[getDirectoryToWatchFromFailedLookupLocationDirectory(dirPath='/projects/myApp/node_modules/react')]", "input_token_count": 433, "output_token_count": 21, "latency": 1.3958828449249268}
{"id": "javascript_39", "result": "[maybeAddJsSyntheticRestParameter(declaration=funcDeclaration, parameters=funcParameters)]", "input_token_count": 457, "output_token_count": 19, "latency": 1.1351051330566406}
{"id": "javascript_40", "result": "[assignOwnDefaults(object='{\"maxItems\": 12}', key='maxItems', objectValue='12', sourceValue='10')]", "input_token_count": 527, "output_token_count": 32, "latency": 1.0737149715423584}
{"id": "javascript_41", "result": "[queue_1(worker=myWorkerFunction, concurrency=5)]", "input_token_count": 475, "output_token_count": 16, "latency": 1.8651838302612305}
{"id": "javascript_42", "result": "[B(t=5, e=\"console.log('Task started')\", n=0.0), B(t=5, e=\"console.log('Queue is saturated')\", n=0.0), B(t=5, e=\"console.log('Queue is unsaturated')\", n=0.0)]", "input_token_count": 492, "output_token_count": 63, "latency": 1.4000377655029297}
{"id": "javascript_43", "result": "[invokeCallback(callback='processResult', error=null, value='Operation successful')]", "input_token_count": 458, "output_token_count": 17, "latency": 1.0889718532562256}
{"id": "javascript_44", "result": "[skipThrough(node='currentNode', st='nodeState', c='processNode')]", "input_token_count": 466, "output_token_count": 19, "latency": 0.9336178302764893}
{"id": "javascript_45", "result": "[Sde(t='https://github.com/yarnpkg/berry', e={'startingCwd': '/home/user/projects'})]", "input_token_count": 479, "output_token_count": 28, "latency": 2.366283893585205}
{"id": "javascript_46", "result": "[vOe(r=\"packageInfo\", e=\"version\", t=\"1.2.3\")]", "input_token_count": 472, "output_token_count": 21, "latency": 1.717094898223877}
{"id": "javascript_47", "result": "[sTe(r='2023-04-01', e='2023-04-15', t='days')]", "input_token_count": 446, "output_token_count": 33, "latency": 2.0297489166259766}
{"id": "javascript_48", "result": "[updateDOMListeners(oldVnode=oldVirtualNode, vnode=newVirtualNode)]", "input_token_count": 437, "output_token_count": 18, "latency": 1.0492630004882812}
{"id": "javascript_49", "result": "[convertEnumeratedValue(key='contenteditable', value='plaintext-only')]", "input_token_count": 421, "output_token_count": 17, "latency": 1.675537109375}
